imagenai/__init__.py
imagenai/generate.py
imagenai-0.1.dist-info/METADATA
imagenai-0.1.dist-info/WHEEL
imagenai-0.1.dist-info/top_level.txt
imagenai-0.1.dist-info/RECORD
