Metadata-Version: 2.1
Name: imagenai
Version: 0.1
Requires-Dist: numpy >=1.26.4
Requires-Dist: matplotlib >=3.8.3
Requires-Dist: requests >=2.31.0
